[
  {
    "id": 1,
    "nome": "Daniel",
    "estrelas": 5,
    "texto": "Jogo incrível!"
  },
  {
    "id": 2,
    "nome": "Juninho",
    "estrelas": 5,
    "texto": "Jogo incrível!"
  },
  {
    "id": 3,
    "nome": "Joao",
    "estrelas": 5,
    "texto": "EU ADORO ANIMOSIDADEe"
  },
  {
    "id": 4,
    "nome": "Username",
    "estrelas": 4,
    "texto": "eu soiu o kauan"
  },
  {
    "id": 5,
    "nome": "Username",
    "estrelas": 1,
    "texto": "zfsdasfazfsa"
  },
  {
    "id": 6,
    "nome": "Username",
    "estrelas": 2,
    "texto": "aasdfasfdsd"
  },
  {
    "id": 7,
    "nome": "Username",
    "estrelas": 3,
    "texto": "asdadadsadsas"
  },
  {
    "id": 8,
    "nome": "Username",
    "estrelas": 3,
    "texto": "oi eu gostei "
  }
]